// 
// Decompiled by Procyon v0.5.36
// 

package de.me.death;

import java.util.Random;
import uiztfzghuzt.kg;
import uiztfzghuzt.nb;

public class gb extends Thread
{
    private g a;
    private l b;
    private static /* synthetic */ int[] c;
    public static boolean e;
    private static final String[] z;
    
    public gb(final g a) {
        final boolean e = gb.e;
        this.setPriority(10);
        this.a = a;
        if (e) {
            boolean a2 = false;
            Label_0035: {
                try {
                    if (nb.a) {
                        a2 = false;
                        break Label_0035;
                    }
                }
                catch (kg kg) {
                    throw kg;
                }
                a2 = true;
            }
            nb.a = a2;
        }
    }
    
    @Override
    public void run() {
        while (true) {
            this.a();
            this.a(this.b(), this.a());
        }
    }
    
    private String a() {
        try {
            switch (d()[this.a.s().ordinal()]) {
                case 3: {
                    return this.c();
                }
                case 1: {
                    break;
                }
                case 2: {
                    return this.a(this.a.t());
                }
                default: {
                    return "";
                }
            }
        }
        catch (kg kg) {
            throw kg;
        }
        return Bot.a.d().b();
    }
    
    private ab b() {
        try {
            if (this.a.r() != de.me.death.b.NONE) {
                return Bot.a.d().a();
            }
        }
        catch (kg kg) {
            throw kg;
        }
        return null;
    }
    
    private void a(final ab p0, final String p1) {
        // 
        // This method could not be decompiled.
        // 
        // Original Bytecode:
        // 
        //     3: istore          5
        //     5: aload_0        
        //     6: getfield        de/me/death/gb.b:Lde/me/death/l;
        //     9: iload           5
        //    11: ifne            587
        //    14: ifnonnull       568
        //    17: goto            21
        //    20: athrow         
        //    21: invokestatic    de/me/death/gb.e:()[I
        //    24: aload_0        
        //    25: getfield        de/me/death/gb.a:Lde/me/death/g;
        //    28: invokevirtual   de/me/death/g.q:()Lde/me/death/d;
        //    31: invokevirtual   de/me/death/d.ordinal:()I
        //    34: iaload         
        //    35: tableswitch {
        //                2: 195
        //                3: 117
        //                4: 143
        //                5: 169
        //                6: 221
        //                7: 247
        //                8: 273
        //                9: 299
        //               10: 325
        //               11: 351
        //               12: 377
        //               13: 403
        //               14: 429
        //               15: 455
        //               16: 481
        //               17: 507
        //               18: 533
        //          default: 559
        //        }
        //   116: athrow         
        //   117: aload_0        
        //   118: new             Lde/me/death/x;
        //   121: dup            
        //   122: aload_2        
        //   123: aload_1        
        //   124: aload_0        
        //   125: getfield        de/me/death/gb.a:Lde/me/death/g;
        //   128: invokespecial   de/me/death/x.<init>:(Ljava/lang/String;Lde/me/death/ab;Lde/me/death/g;)V
        //   131: putfield        de/me/death/gb.b:Lde/me/death/l;
        //   134: iload           5
        //   136: ifeq            594
        //   139: goto            143
        //   142: athrow         
        //   143: aload_0        
        //   144: new             Lde/me/death/y;
        //   147: dup            
        //   148: aload_2        
        //   149: aload_1        
        //   150: aload_0        
        //   151: getfield        de/me/death/gb.a:Lde/me/death/g;
        //   154: invokespecial   de/me/death/y.<init>:(Ljava/lang/String;Lde/me/death/ab;Lde/me/death/g;)V
        //   157: putfield        de/me/death/gb.b:Lde/me/death/l;
        //   160: iload           5
        //   162: ifeq            594
        //   165: goto            169
        //   168: athrow         
        //   169: aload_0        
        //   170: new             Lde/me/death/u;
        //   173: dup            
        //   174: aload_2        
        //   175: aload_1        
        //   176: aload_0        
        //   177: getfield        de/me/death/gb.a:Lde/me/death/g;
        //   180: invokespecial   de/me/death/u.<init>:(Ljava/lang/String;Lde/me/death/ab;Lde/me/death/g;)V
        //   183: putfield        de/me/death/gb.b:Lde/me/death/l;
        //   186: iload           5
        //   188: ifeq            594
        //   191: goto            195
        //   194: athrow         
        //   195: aload_0        
        //   196: new             Lde/me/death/v;
        //   199: dup            
        //   200: aload_2        
        //   201: aload_1        
        //   202: aload_0        
        //   203: getfield        de/me/death/gb.a:Lde/me/death/g;
        //   206: invokespecial   de/me/death/v.<init>:(Ljava/lang/String;Lde/me/death/ab;Lde/me/death/g;)V
        //   209: putfield        de/me/death/gb.b:Lde/me/death/l;
        //   212: iload           5
        //   214: ifeq            594
        //   217: goto            221
        //   220: athrow         
        //   221: aload_0        
        //   222: new             Lde/me/death/m;
        //   225: dup            
        //   226: aload_2        
        //   227: aload_1        
        //   228: aload_0        
        //   229: getfield        de/me/death/gb.a:Lde/me/death/g;
        //   232: invokespecial   de/me/death/m.<init>:(Ljava/lang/String;Lde/me/death/ab;Lde/me/death/g;)V
        //   235: putfield        de/me/death/gb.b:Lde/me/death/l;
        //   238: iload           5
        //   240: ifeq            594
        //   243: goto            247
        //   246: athrow         
        //   247: aload_0        
        //   248: new             Lde/me/death/n;
        //   251: dup            
        //   252: aload_2        
        //   253: aload_1        
        //   254: aload_0        
        //   255: getfield        de/me/death/gb.a:Lde/me/death/g;
        //   258: invokespecial   de/me/death/n.<init>:(Ljava/lang/String;Lde/me/death/ab;Lde/me/death/g;)V
        //   261: putfield        de/me/death/gb.b:Lde/me/death/l;
        //   264: iload           5
        //   266: ifeq            594
        //   269: goto            273
        //   272: athrow         
        //   273: aload_0        
        //   274: new             Lde/me/death/o;
        //   277: dup            
        //   278: aload_2        
        //   279: aload_1        
        //   280: aload_0        
        //   281: getfield        de/me/death/gb.a:Lde/me/death/g;
        //   284: invokespecial   de/me/death/o.<init>:(Ljava/lang/String;Lde/me/death/ab;Lde/me/death/g;)V
        //   287: putfield        de/me/death/gb.b:Lde/me/death/l;
        //   290: iload           5
        //   292: ifeq            594
        //   295: goto            299
        //   298: athrow         
        //   299: aload_0        
        //   300: new             Lde/me/death/p;
        //   303: dup            
        //   304: aload_2        
        //   305: aload_1        
        //   306: aload_0        
        //   307: getfield        de/me/death/gb.a:Lde/me/death/g;
        //   310: invokespecial   de/me/death/p.<init>:(Ljava/lang/String;Lde/me/death/ab;Lde/me/death/g;)V
        //   313: putfield        de/me/death/gb.b:Lde/me/death/l;
        //   316: iload           5
        //   318: ifeq            594
        //   321: goto            325
        //   324: athrow         
        //   325: aload_0        
        //   326: new             Lde/me/death/q;
        //   329: dup            
        //   330: aload_2        
        //   331: aload_1        
        //   332: aload_0        
        //   333: getfield        de/me/death/gb.a:Lde/me/death/g;
        //   336: invokespecial   de/me/death/q.<init>:(Ljava/lang/String;Lde/me/death/ab;Lde/me/death/g;)V
        //   339: putfield        de/me/death/gb.b:Lde/me/death/l;
        //   342: iload           5
        //   344: ifeq            594
        //   347: goto            351
        //   350: athrow         
        //   351: aload_0        
        //   352: new             Lde/me/death/r;
        //   355: dup            
        //   356: aload_2        
        //   357: aload_1        
        //   358: aload_0        
        //   359: getfield        de/me/death/gb.a:Lde/me/death/g;
        //   362: invokespecial   de/me/death/r.<init>:(Ljava/lang/String;Lde/me/death/ab;Lde/me/death/g;)V
        //   365: putfield        de/me/death/gb.b:Lde/me/death/l;
        //   368: iload           5
        //   370: ifeq            594
        //   373: goto            377
        //   376: athrow         
        //   377: aload_0        
        //   378: new             Lde/me/death/r;
        //   381: dup            
        //   382: aload_2        
        //   383: aload_1        
        //   384: aload_0        
        //   385: getfield        de/me/death/gb.a:Lde/me/death/g;
        //   388: invokespecial   de/me/death/r.<init>:(Ljava/lang/String;Lde/me/death/ab;Lde/me/death/g;)V
        //   391: putfield        de/me/death/gb.b:Lde/me/death/l;
        //   394: iload           5
        //   396: ifeq            594
        //   399: goto            403
        //   402: athrow         
        //   403: aload_0        
        //   404: new             Lde/me/death/r;
        //   407: dup            
        //   408: aload_2        
        //   409: aload_1        
        //   410: aload_0        
        //   411: getfield        de/me/death/gb.a:Lde/me/death/g;
        //   414: invokespecial   de/me/death/r.<init>:(Ljava/lang/String;Lde/me/death/ab;Lde/me/death/g;)V
        //   417: putfield        de/me/death/gb.b:Lde/me/death/l;
        //   420: iload           5
        //   422: ifeq            594
        //   425: goto            429
        //   428: athrow         
        //   429: aload_0        
        //   430: new             Lde/me/death/r;
        //   433: dup            
        //   434: aload_2        
        //   435: aload_1        
        //   436: aload_0        
        //   437: getfield        de/me/death/gb.a:Lde/me/death/g;
        //   440: invokespecial   de/me/death/r.<init>:(Ljava/lang/String;Lde/me/death/ab;Lde/me/death/g;)V
        //   443: putfield        de/me/death/gb.b:Lde/me/death/l;
        //   446: iload           5
        //   448: ifeq            594
        //   451: goto            455
        //   454: athrow         
        //   455: aload_0        
        //   456: new             Lde/me/death/r;
        //   459: dup            
        //   460: aload_2        
        //   461: aload_1        
        //   462: aload_0        
        //   463: getfield        de/me/death/gb.a:Lde/me/death/g;
        //   466: invokespecial   de/me/death/r.<init>:(Ljava/lang/String;Lde/me/death/ab;Lde/me/death/g;)V
        //   469: putfield        de/me/death/gb.b:Lde/me/death/l;
        //   472: iload           5
        //   474: ifeq            594
        //   477: goto            481
        //   480: athrow         
        //   481: aload_0        
        //   482: new             Lde/me/death/s;
        //   485: dup            
        //   486: aload_2        
        //   487: aload_1        
        //   488: aload_0        
        //   489: getfield        de/me/death/gb.a:Lde/me/death/g;
        //   492: invokespecial   de/me/death/s.<init>:(Ljava/lang/String;Lde/me/death/ab;Lde/me/death/g;)V
        //   495: putfield        de/me/death/gb.b:Lde/me/death/l;
        //   498: iload           5
        //   500: ifeq            594
        //   503: goto            507
        //   506: athrow         
        //   507: aload_0        
        //   508: new             Lde/me/death/t;
        //   511: dup            
        //   512: aload_2        
        //   513: aload_1        
        //   514: aload_0        
        //   515: getfield        de/me/death/gb.a:Lde/me/death/g;
        //   518: invokespecial   de/me/death/t.<init>:(Ljava/lang/String;Lde/me/death/ab;Lde/me/death/g;)V
        //   521: putfield        de/me/death/gb.b:Lde/me/death/l;
        //   524: iload           5
        //   526: ifeq            594
        //   529: goto            533
        //   532: athrow         
        //   533: aload_0        
        //   534: new             Lde/me/death/t;
        //   537: dup            
        //   538: aload_2        
        //   539: aload_1        
        //   540: aload_0        
        //   541: getfield        de/me/death/gb.a:Lde/me/death/g;
        //   544: invokespecial   de/me/death/t.<init>:(Ljava/lang/String;Lde/me/death/ab;Lde/me/death/g;)V
        //   547: putfield        de/me/death/gb.b:Lde/me/death/l;
        //   550: iload           5
        //   552: ifeq            594
        //   555: goto            559
        //   558: athrow         
        //   559: iload           5
        //   561: ifeq            594
        //   564: goto            568
        //   567: athrow         
        //   568: aload_0        
        //   569: getfield        de/me/death/gb.b:Lde/me/death/l;
        //   572: aload_0        
        //   573: invokespecial   de/me/death/gb.a:()Ljava/lang/String;
        //   576: invokevirtual   de/me/death/l.a:(Ljava/lang/String;)V
        //   579: aload_0        
        //   580: getfield        de/me/death/gb.b:Lde/me/death/l;
        //   583: goto            587
        //   586: athrow         
        //   587: aload_0        
        //   588: invokespecial   de/me/death/gb.b:()Lde/me/death/ab;
        //   591: invokevirtual   de/me/death/l.a:(Lde/me/death/ab;)V
        //   594: aload_0        
        //   595: iload           5
        //   597: ifne            668
        //   600: getfield        de/me/death/gb.a:Lde/me/death/g;
        //   603: invokevirtual   de/me/death/g.e:()Z
        //   606: ifeq            667
        //   609: goto            613
        //   612: athrow         
        //   613: iconst_0       
        //   614: istore_3       
        //   615: iload           5
        //   617: ifeq            646
        //   620: aload_0        
        //   621: getfield        de/me/death/gb.b:Lde/me/death/l;
        //   624: invokevirtual   de/me/death/l.a:()V
        //   627: goto            643
        //   630: astore          4
        //   632: aload_0        
        //   633: getfield        de/me/death/gb.b:Lde/me/death/l;
        //   636: aload_0        
        //   637: invokespecial   de/me/death/gb.b:()Lde/me/death/ab;
        //   640: invokevirtual   de/me/death/l.a:(Lde/me/death/ab;)V
        //   643: iinc            3, 1
        //   646: iload_3        
        //   647: aload_0        
        //   648: getfield        de/me/death/gb.a:Lde/me/death/g;
        //   651: invokevirtual   de/me/death/g.d:()I
        //   654: if_icmplt       620
        //   657: iload           5
        //   659: ifne            627
        //   662: iload           5
        //   664: ifeq            678
        //   667: aload_0        
        //   668: getfield        de/me/death/gb.b:Lde/me/death/l;
        //   671: invokevirtual   de/me/death/l.a:()V
        //   674: goto            678
        //   677: astore_3       
        //   678: return         
        //    StackMapTable: 00 36 FF 00 14 00 06 07 00 02 07 00 A1 07 00 A3 00 00 01 00 01 07 00 5F 00 F7 00 5E 07 00 5F 00 58 07 00 5F 00 58 07 00 5F 00 58 07 00 5F 00 58 07 00 5F 00 58 07 00 5F 00 58 07 00 5F 00 58 07 00 5F 00 58 07 00 5F 00 58 07 00 5F 00 58 07 00 5F 00 58 07 00 5F 00 58 07 00 5F 00 58 07 00 5F 00 58 07 00 5F 00 58 07 00 5F 00 58 07 00 5F 00 58 07 00 5F 00 47 07 00 5F 00 51 07 00 5F 40 07 00 92 06 51 07 00 5F 00 FF 00 06 00 06 07 00 02 07 00 A1 07 00 A3 01 00 01 00 00 06 42 07 00 5F 0C 02 FF 00 14 00 06 07 00 02 07 00 A1 07 00 A3 00 00 01 00 00 40 07 00 02 48 07 00 5F 00
        //    Exceptions:
        //  Try           Handler
        //  Start  End    Start  End    Type                 
        //  -----  -----  -----  -----  ---------------------
        //  594    609    612    613    Ljava/lang/Exception;
        //  559    583    586    587    Ljava/lang/Exception;
        //  533    564    567    568    Ljava/lang/Exception;
        //  507    555    558    559    Ljava/lang/Exception;
        //  481    529    532    533    Ljava/lang/Exception;
        //  455    503    506    507    Ljava/lang/Exception;
        //  429    477    480    481    Ljava/lang/Exception;
        //  403    451    454    455    Ljava/lang/Exception;
        //  377    425    428    429    Ljava/lang/Exception;
        //  351    399    402    403    Ljava/lang/Exception;
        //  325    373    376    377    Ljava/lang/Exception;
        //  299    347    350    351    Ljava/lang/Exception;
        //  273    321    324    325    Ljava/lang/Exception;
        //  247    295    298    299    Ljava/lang/Exception;
        //  221    269    272    273    Ljava/lang/Exception;
        //  195    243    246    247    Ljava/lang/Exception;
        //  169    217    220    221    Ljava/lang/Exception;
        //  143    191    194    195    Ljava/lang/Exception;
        //  117    165    168    169    Ljava/lang/Exception;
        //  21     139    142    143    Ljava/lang/Exception;
        //  14     116    116    117    Ljava/lang/Exception;
        //  5      17     20     21     Ljava/lang/Exception;
        //  620    627    630    643    Ljava/lang/Exception;
        //  667    674    677    678    Ljava/lang/Exception;
        // 
        // The error that occurred was:
        // 
        // java.lang.IllegalStateException: Expression is linked from several locations: Label_0021:
        //     at com.strobel.decompiler.ast.Error.expressionLinkedFromMultipleLocations(Error.java:27)
        //     at com.strobel.decompiler.ast.AstOptimizer.mergeDisparateObjectInitializations(AstOptimizer.java:2596)
        //     at com.strobel.decompiler.ast.AstOptimizer.optimize(AstOptimizer.java:235)
        //     at com.strobel.decompiler.ast.AstOptimizer.optimize(AstOptimizer.java:42)
        //     at com.strobel.decompiler.languages.java.ast.AstMethodBodyBuilder.createMethodBody(AstMethodBodyBuilder.java:214)
        //     at com.strobel.decompiler.languages.java.ast.AstMethodBodyBuilder.createMethodBody(AstMethodBodyBuilder.java:99)
        //     at com.strobel.decompiler.languages.java.ast.AstBuilder.createMethodBody(AstBuilder.java:782)
        //     at com.strobel.decompiler.languages.java.ast.AstBuilder.createMethod(AstBuilder.java:675)
        //     at com.strobel.decompiler.languages.java.ast.AstBuilder.addTypeMembers(AstBuilder.java:552)
        //     at com.strobel.decompiler.languages.java.ast.AstBuilder.createTypeCore(AstBuilder.java:519)
        //     at com.strobel.decompiler.languages.java.ast.AstBuilder.createTypeNoCache(AstBuilder.java:161)
        //     at com.strobel.decompiler.languages.java.ast.AstBuilder.createType(AstBuilder.java:150)
        //     at com.strobel.decompiler.languages.java.ast.AstBuilder.addType(AstBuilder.java:125)
        //     at com.strobel.decompiler.languages.java.JavaLanguage.buildAst(JavaLanguage.java:71)
        //     at com.strobel.decompiler.languages.java.JavaLanguage.decompileType(JavaLanguage.java:59)
        //     at com.strobel.decompiler.DecompilerDriver.decompileType(DecompilerDriver.java:330)
        //     at com.strobel.decompiler.DecompilerDriver.decompileJar(DecompilerDriver.java:251)
        //     at com.strobel.decompiler.DecompilerDriver.main(DecompilerDriver.java:126)
        // 
        throw new IllegalStateException("An error occurred while decompiling this method.");
    }
    
    private String c() {
        StringBuilder sb2 = null;
    Label_0221_Outer:
        while (true) {
            final boolean e = gb.e;
            final StringBuilder sb = new StringBuilder();
            final String[] array = { "Build", "Tower", "Craft", "Plays", "Nitro", "Hyper", "Super", "Beach", "Worms", "Actor", "Elder", "Games", "Slime", "Crazy", "_Itz", "Mine", "Craft" };
            final String[] array2 = { "HD", "YT", "69", "99", "LP", "50", "XD", "11", "HD", "LP", "YT", "88" };
            final Random random = new Random();
            int n = 0;
            while (true) {
                while (true) {
                    Label_0225: {
                        try {
                            if (!e) {
                                break Label_0225;
                            }
                            sb.append(array[random.nextInt(array.length)]);
                        }
                        catch (kg kg) {
                            throw kg;
                        }
                        ++n;
                    }
                    if (n < 2) {
                        continue Label_0221_Outer;
                    }
                    break;
                }
                sb.append(array2[random.nextInt(array2.length)]);
                sb2 = sb;
                if (!e) {
                    break;
                }
                continue;
            }
        }
        return sb2.toString();
    }
    
    private String a(final int n) {
        String s = null;
    Label_0061_Outer:
        while (true) {
            final boolean e = gb.e;
            final Random random = new Random();
            final char[] charArray = "abcdefghijklmnopqrstuvwxyzABCDEFGHIJKLMNOPQRSTUVWXYZ0123456789_".toCharArray();
            String obj = "";
            int n2 = 0;
            while (true) {
                while (true) {
                    Label_0066: {
                        try {
                            if (!e) {
                                break Label_0066;
                            }
                            new StringBuilder(String.valueOf(obj)).append(charArray[random.nextInt(charArray.length)]).toString();
                        }
                        catch (kg kg) {
                            throw kg;
                        }
                        obj = s;
                        ++n2;
                    }
                    if (n2 < n) {
                        continue Label_0061_Outer;
                    }
                    break;
                }
                s = obj;
                if (!e) {
                    break;
                }
                continue;
            }
        }
        return s;
    }
    
    static /* synthetic */ int[] d() {
        int[] c = null;
        Label_0026: {
            Label_0019: {
                int[] array;
                try {
                    array = (c = gb.c);
                    if (gb.e) {
                        break Label_0026;
                    }
                    if (array != null) {
                        return array;
                    }
                    break Label_0019;
                }
                catch (NoSuchFieldError noSuchFieldError) {
                    throw noSuchFieldError;
                }
                try {
                    if (array != null) {
                        return array;
                    }
                }
                catch (NoSuchFieldError noSuchFieldError2) {
                    throw noSuchFieldError2;
                }
            }
            c = new int[de.me.death.c.values().length];
        }
        final int[] c2 = c;
        try {
            c2[de.me.death.c.FAKENICKS.ordinal()] = 3;
        }
        catch (NoSuchFieldError noSuchFieldError3) {}
        try {
            c2[de.me.death.c.NICKS.ordinal()] = 1;
        }
        catch (NoSuchFieldError noSuchFieldError4) {}
        try {
            c2[de.me.death.c.RANDOM.ordinal()] = 2;
        }
        catch (NoSuchFieldError noSuchFieldError5) {}
        return gb.c = c2;
    }
    
    static {
        final String[] array = new String[26];
        int n26;
        int n25;
        int n24;
        int n23;
        int n22;
        int n21;
        int n20;
        int n19;
        int n18;
        int n17;
        int n16;
        int n15;
        int n14;
        int n13;
        int n12;
        int n11;
        int n10;
        int n9;
        int n8;
        int n7;
        int n6;
        int n5;
        int n4;
        int n3;
        int n2;
        int n = n2 = (n3 = (n4 = (n5 = (n6 = (n7 = (n8 = (n9 = (n10 = (n11 = (n12 = (n13 = (n14 = (n15 = (n16 = (n17 = (n18 = (n19 = (n20 = (n21 = (n22 = (n23 = (n24 = (n25 = (n26 = 0))))))))))))))))))))))));
        String s = "j\u0012q=\"";
        int n27 = -1;
        String intern = null;
    Label_0515_Outer:
        while (true) {
            final char[] charArray = s.toCharArray();
            int length;
            int n29;
            final int n28 = n29 = (length = charArray.length);
            int n30 = 0;
            while (true) {
                Label_0589: {
                    if (n28 > 1) {
                        break Label_0589;
                    }
                    length = (n29 = n30);
                    do {
                        final char c = charArray[n29];
                        char c2 = '\0';
                        switch (n30 % 5) {
                            case 0: {
                                c2 = '$';
                                break;
                            }
                            case 1: {
                                c2 = '{';
                                break;
                            }
                            case 2: {
                                c2 = '\u0005';
                                break;
                            }
                            case 3: {
                                c2 = 'O';
                                break;
                            }
                            default: {
                                c2 = 'M';
                                break;
                            }
                        }
                        charArray[length] = (char)(c ^ c2);
                        ++n30;
                    } while (n28 == 0);
                }
                if (n28 > n30) {
                    continue;
                }
                break;
            }
            intern = new String(charArray).intern();
            switch (n27) {
                default: {
                    array[n2] = intern;
                    n = (n2 = (n3 = (n4 = (n5 = (n6 = (n7 = (n8 = (n9 = (n10 = (n11 = (n12 = (n13 = (n14 = (n15 = (n16 = (n17 = (n18 = (n19 = (n20 = (n21 = (n22 = (n23 = (n24 = (n25 = (n26 = 1)))))))))))))))))))))))));
                    s = "e\u0018q ?";
                    n27 = 0;
                    continue Label_0515_Outer;
                }
                case 0: {
                    array[n] = intern;
                    n = (n2 = (n3 = (n4 = (n5 = (n6 = (n7 = (n8 = (n9 = (n10 = (n11 = (n12 = (n13 = (n14 = (n15 = (n16 = (n17 = (n18 = (n19 = (n20 = (n21 = (n22 = (n23 = (n24 = (n25 = (n26 = 2)))))))))))))))))))))))));
                    s = "a\u0017a*?";
                    n27 = 1;
                    continue Label_0515_Outer;
                }
                case 1: {
                    array[n3] = intern;
                    n = (n2 = (n3 = (n4 = (n5 = (n6 = (n7 = (n8 = (n9 = (n10 = (n11 = (n12 = (n13 = (n14 = (n15 = (n16 = (n17 = (n18 = (n19 = (n20 = (n21 = (n22 = (n23 = (n24 = (n25 = (n26 = 3)))))))))))))))))))))))));
                    s = "}/";
                    n27 = 2;
                    continue Label_0515_Outer;
                }
                case 2: {
                    array[n4] = intern;
                    n = (n2 = (n3 = (n4 = (n5 = (n6 = (n7 = (n8 = (n9 = (n10 = (n11 = (n12 = (n13 = (n14 = (n15 = (n16 = (n17 = (n18 = (n19 = (n20 = (n21 = (n22 = (n23 = (n24 = (n25 = (n26 = 4)))))))))))))))))))))))));
                    s = "l?";
                    n27 = 3;
                    continue Label_0515_Outer;
                }
                case 3: {
                    array[n5] = intern;
                    n = (n2 = (n3 = (n4 = (n5 = (n6 = (n7 = (n8 = (n9 = (n10 = (n11 = (n12 = (n13 = (n14 = (n15 = (n16 = (n17 = (n18 = (n19 = (n20 = (n21 = (n22 = (n23 = (n24 = (n25 = (n26 = 5)))))))))))))))))))))))));
                    s = "\u001dB";
                    n27 = 4;
                    continue Label_0515_Outer;
                }
                case 4: {
                    array[n6] = intern;
                    n = (n2 = (n3 = (n4 = (n5 = (n6 = (n7 = (n8 = (n9 = (n10 = (n11 = (n12 = (n13 = (n14 = (n15 = (n16 = (n17 = (n18 = (n19 = (n20 = (n21 = (n22 = (n23 = (n24 = (n25 = (n26 = 6)))))))))))))))))))))))));
                    s = "t\u0017d6>";
                    n27 = 5;
                    continue Label_0515_Outer;
                }
                case 5: {
                    array[n7] = intern;
                    n = (n2 = (n3 = (n4 = (n5 = (n6 = (n7 = (n8 = (n9 = (n10 = (n11 = (n12 = (n13 = (n14 = (n15 = (n16 = (n17 = (n18 = (n19 = (n20 = (n21 = (n22 = (n23 = (n24 = (n25 = (n26 = 7)))))))))))))))))))))))));
                    s = "\u0015J";
                    n27 = 6;
                    continue Label_0515_Outer;
                }
                case 6: {
                    array[n8] = intern;
                    n = (n2 = (n3 = (n4 = (n5 = (n6 = (n7 = (n8 = (n9 = (n10 = (n11 = (n12 = (n13 = (n14 = (n15 = (n16 = (n17 = (n18 = (n19 = (n20 = (n21 = (n22 = (n23 = (n24 = (n25 = (n26 = 8)))))))))))))))))))))))));
                    s = "f\u001ed,%";
                    n27 = 7;
                    continue Label_0515_Outer;
                }
                case 7: {
                    array[n9] = intern;
                    n = (n2 = (n3 = (n4 = (n5 = (n6 = (n7 = (n8 = (n9 = (n10 = (n11 = (n12 = (n13 = (n14 = (n15 = (n16 = (n17 = (n18 = (n19 = (n20 = (n21 = (n22 = (n23 = (n24 = (n25 = (n26 = 9)))))))))))))))))))))))));
                    s = "w\u000eu*?";
                    n27 = 8;
                    continue Label_0515_Outer;
                }
                case 8: {
                    array[n10] = intern;
                    n = (n2 = (n3 = (n4 = (n5 = (n6 = (n7 = (n8 = (n9 = (n10 = (n11 = (n12 = (n13 = (n14 = (n15 = (n16 = (n17 = (n18 = (n19 = (n20 = (n21 = (n22 = (n23 = (n24 = (n25 = (n26 = 10)))))))))))))))))))))))));
                    s = "\u0011K";
                    n27 = 9;
                    continue Label_0515_Outer;
                }
                case 9: {
                    array[n11] = intern;
                    n = (n2 = (n3 = (n4 = (n5 = (n6 = (n7 = (n8 = (n9 = (n10 = (n11 = (n12 = (n13 = (n14 = (n15 = (n16 = (n17 = (n18 = (n19 = (n20 = (n21 = (n22 = (n23 = (n24 = (n25 = (n26 = 11)))))))))))))))))))))))));
                    s = "\u001cC";
                    n27 = 10;
                    continue Label_0515_Outer;
                }
                case 10: {
                    array[n12] = intern;
                    n = (n2 = (n3 = (n4 = (n5 = (n6 = (n7 = (n8 = (n9 = (n10 = (n11 = (n12 = (n13 = (n14 = (n15 = (n16 = (n17 = (n18 = (n19 = (n20 = (n21 = (n22 = (n23 = (n24 = (n25 = (n26 = 12)))))))))))))))))))))))));
                    s = "p\u0014r*?";
                    n27 = 11;
                    continue Label_0515_Outer;
                }
                case 11: {
                    array[n13] = intern;
                    n = (n2 = (n3 = (n4 = (n5 = (n6 = (n7 = (n8 = (n9 = (n10 = (n11 = (n12 = (n13 = (n14 = (n15 = (n16 = (n17 = (n18 = (n19 = (n20 = (n21 = (n22 = (n23 = (n24 = (n25 = (n26 = 13)))))))))))))))))))))))));
                    s = "w\u0017l\"(";
                    n27 = 12;
                    continue Label_0515_Outer;
                }
                case 12: {
                    array[n14] = intern;
                    n = (n2 = (n3 = (n4 = (n5 = (n6 = (n7 = (n8 = (n9 = (n10 = (n11 = (n12 = (n13 = (n14 = (n15 = (n16 = (n17 = (n18 = (n19 = (n20 = (n21 = (n22 = (n23 = (n24 = (n25 = (n26 = 14)))))))))))))))))))))))));
                    s = "h+";
                    n27 = 13;
                    continue Label_0515_Outer;
                }
                case 13: {
                    array[n15] = intern;
                    n = (n2 = (n3 = (n4 = (n5 = (n6 = (n7 = (n8 = (n9 = (n10 = (n11 = (n12 = (n13 = (n14 = (n15 = (n16 = (n17 = (n18 = (n19 = (n20 = (n21 = (n22 = (n23 = (n24 = (n25 = (n26 = 15)))))))))))))))))))))))));
                    s = "l\u0002u*?";
                    n27 = 14;
                    continue Label_0515_Outer;
                }
                case 14: {
                    array[n16] = intern;
                    n = (n2 = (n3 = (n4 = (n5 = (n6 = (n7 = (n8 = (n9 = (n10 = (n11 = (n12 = (n13 = (n14 = (n15 = (n16 = (n17 = (n18 = (n19 = (n20 = (n21 = (n22 = (n23 = (n24 = (n25 = (n26 = 16)))))))))))))))))))))))));
                    s = "c\u001ah*>";
                    n27 = 15;
                    continue Label_0515_Outer;
                }
                case 15: {
                    array[n17] = intern;
                    n = (n2 = (n3 = (n4 = (n5 = (n6 = (n7 = (n8 = (n9 = (n10 = (n11 = (n12 = (n13 = (n14 = (n15 = (n16 = (n17 = (n18 = (n19 = (n20 = (n21 = (n22 = (n23 = (n24 = (n25 = (n26 = 17)))))))))))))))))))))))));
                    s = "g\td)9";
                    n27 = 16;
                    continue Label_0515_Outer;
                }
                case 16: {
                    array[n18] = intern;
                    n = (n2 = (n3 = (n4 = (n5 = (n6 = (n7 = (n8 = (n9 = (n10 = (n11 = (n12 = (n13 = (n14 = (n15 = (n16 = (n17 = (n18 = (n19 = (n20 = (n21 = (n22 = (n23 = (n24 = (n25 = (n26 = 18)))))))))))))))))))))))));
                    s = "{2q5";
                    n27 = 17;
                    continue Label_0515_Outer;
                }
                case 17: {
                    array[n19] = intern;
                    n = (n2 = (n3 = (n4 = (n5 = (n6 = (n7 = (n8 = (n9 = (n10 = (n11 = (n12 = (n13 = (n14 = (n15 = (n16 = (n17 = (n18 = (n19 = (n20 = (n21 = (n22 = (n23 = (n24 = (n25 = (n26 = 19)))))))))))))))))))))))));
                    s = "\u0012B";
                    n27 = 18;
                    continue Label_0515_Outer;
                }
                case 18: {
                    array[n20] = intern;
                    n = (n2 = (n3 = (n4 = (n5 = (n6 = (n7 = (n8 = (n9 = (n10 = (n11 = (n12 = (n13 = (n14 = (n15 = (n16 = (n17 = (n18 = (n19 = (n20 = (n21 = (n22 = (n23 = (n24 = (n25 = (n26 = 20)))))))))))))))))))))))));
                    s = "s\u0014w\">";
                    n27 = 19;
                    continue Label_0515_Outer;
                }
                case 19: {
                    array[n21] = intern;
                    n = (n2 = (n3 = (n4 = (n5 = (n6 = (n7 = (n8 = (n9 = (n10 = (n11 = (n12 = (n13 = (n14 = (n15 = (n16 = (n17 = (n18 = (n19 = (n20 = (n21 = (n22 = (n23 = (n24 = (n25 = (n26 = 21)))))))))))))))))))))))));
                    s = "g\td54";
                    n27 = 20;
                    continue Label_0515_Outer;
                }
                case 20: {
                    array[n22] = intern;
                    n = (n2 = (n3 = (n4 = (n5 = (n6 = (n7 = (n8 = (n9 = (n10 = (n11 = (n12 = (n13 = (n14 = (n15 = (n16 = (n17 = (n18 = (n19 = (n20 = (n21 = (n22 = (n23 = (n24 = (n25 = (n26 = 22)))))))))))))))))))))))));
                    s = "|?";
                    n27 = 21;
                    continue Label_0515_Outer;
                }
                case 21: {
                    array[n23] = intern;
                    n = (n2 = (n3 = (n4 = (n5 = (n6 = (n7 = (n8 = (n9 = (n10 = (n11 = (n12 = (n13 = (n14 = (n15 = (n16 = (n17 = (n18 = (n19 = (n20 = (n21 = (n22 = (n23 = (n24 = (n25 = (n26 = 23)))))))))))))))))))))))));
                    s = "f\u000el#)";
                    n27 = 22;
                    continue Label_0515_Outer;
                }
                case 22: {
                    array[n24] = intern;
                    n = (n2 = (n3 = (n4 = (n5 = (n6 = (n7 = (n8 = (n9 = (n10 = (n11 = (n12 = (n13 = (n14 = (n15 = (n16 = (n17 = (n18 = (n19 = (n20 = (n21 = (n22 = (n23 = (n24 = (n25 = (n26 = 24)))))))))))))))))))))))));
                    s = "i\u0012k*";
                    n27 = 23;
                    continue Label_0515_Outer;
                }
                case 23: {
                    array[n25] = intern;
                    n = (n2 = (n3 = (n4 = (n5 = (n6 = (n7 = (n8 = (n9 = (n10 = (n11 = (n12 = (n13 = (n14 = (n15 = (n16 = (n17 = (n18 = (n19 = (n20 = (n21 = (n22 = (n23 = (n24 = (n25 = (n26 = 25)))))))))))))))))))))))));
                    s = "E\u0019f+(B\u001cm&'O\u0017h!\"T\nw<9Q\rr74^:G\f\ta=B\u0007\u0004n0I\u0002\u0003k+T\u001d\u001ep.S\u0018\u0015}!5~\u007f\u0017O0yz\u001cBZ";
                    n27 = 24;
                    continue Label_0515_Outer;
                }
                case 24: {
                    break Label_0515_Outer;
                }
            }
        }
        array[n26] = intern;
        z = new String[] { "Nitro", "Actor", "Elder", "YT", "HD", "99", "Plays", "11", "Beach", "Super", "50", "88", "Tower", "Slime", "LP", "Hyper", "Games", "Craft", "_Itz", "69", "Worms", "Crazy", "XD", "Build", "Mine", "abcdefghijklmnopqrstuvwxyzABCDEFGHIJKLMNOPQRSTUVWXYZ0123456789_" };
    }
}
