// 
// Decompiled by Procyon v0.5.36
// 

package uiztfzghuzt;

import java.util.Date;
import java.text.ParsePosition;
import java.util.TimeZone;

public class zf
{
    private static final TimeZone a;
    public static boolean b;
    private static final String[] z;
    
    public static Date a(final String p0, final ParsePosition p1) {
        // 
        // This method could not be decompiled.
        // 
        // Original Bytecode:
        // 
        //     3: istore          18
        //     5: aconst_null    
        //     6: astore_2       
        //     7: aload_1        
        //     8: invokevirtual   java/text/ParsePosition.getIndex:()I
        //    11: istore_3       
        //    12: aload_0        
        //    13: iload_3        
        //    14: iinc            3, 4
        //    17: iload_3        
        //    18: invokestatic    uiztfzghuzt/zf.a:(Ljava/lang/String;II)I
        //    21: istore          4
        //    23: aload_0        
        //    24: iload_3        
        //    25: bipush          45
        //    27: invokestatic    uiztfzghuzt/zf.a:(Ljava/lang/String;IC)Z
        //    30: iload           18
        //    32: ifne            54
        //    35: ifeq            45
        //    38: goto            42
        //    41: athrow         
        //    42: iinc            3, 1
        //    45: aload_0        
        //    46: iload_3        
        //    47: iinc            3, 2
        //    50: iload_3        
        //    51: invokestatic    uiztfzghuzt/zf.a:(Ljava/lang/String;II)I
        //    54: istore          5
        //    56: aload_0        
        //    57: iload_3        
        //    58: bipush          45
        //    60: invokestatic    uiztfzghuzt/zf.a:(Ljava/lang/String;IC)Z
        //    63: iload           18
        //    65: ifne            87
        //    68: ifeq            78
        //    71: goto            75
        //    74: athrow         
        //    75: iinc            3, 1
        //    78: aload_0        
        //    79: iload_3        
        //    80: iinc            3, 2
        //    83: iload_3        
        //    84: invokestatic    uiztfzghuzt/zf.a:(Ljava/lang/String;II)I
        //    87: istore          6
        //    89: iconst_0       
        //    90: istore          7
        //    92: iconst_0       
        //    93: istore          8
        //    95: iconst_0       
        //    96: istore          9
        //    98: iconst_0       
        //    99: istore          10
        //   101: aload_0        
        //   102: iload_3        
        //   103: bipush          84
        //   105: invokestatic    uiztfzghuzt/zf.a:(Ljava/lang/String;IC)Z
        //   108: istore          11
        //   110: iload           11
        //   112: iload           18
        //   114: ifne            175
        //   117: ifne            173
        //   120: goto            124
        //   123: athrow         
        //   124: aload_0        
        //   125: invokevirtual   java/lang/String.length:()I
        //   128: iload           18
        //   130: ifne            175
        //   133: goto            137
        //   136: athrow         
        //   137: iload_3        
        //   138: if_icmpgt       173
        //   141: goto            145
        //   144: athrow         
        //   145: new             Ljava/util/GregorianCalendar;
        //   148: dup            
        //   149: iload           4
        //   151: iload           5
        //   153: iconst_1       
        //   154: isub           
        //   155: iload           6
        //   157: invokespecial   java/util/GregorianCalendar.<init>:(III)V
        //   160: astore          12
        //   162: aload_1        
        //   163: iload_3        
        //   164: invokevirtual   java/text/ParsePosition.setIndex:(I)V
        //   167: aload           12
        //   169: invokevirtual   java/util/Calendar.getTime:()Ljava/util/Date;
        //   172: areturn        
        //   173: iload           11
        //   175: iload           18
        //   177: ifne            531
        //   180: ifeq            527
        //   183: goto            187
        //   186: athrow         
        //   187: aload_0        
        //   188: iinc            3, 1
        //   191: iload_3        
        //   192: iinc            3, 2
        //   195: iload_3        
        //   196: invokestatic    uiztfzghuzt/zf.a:(Ljava/lang/String;II)I
        //   199: istore          7
        //   201: aload_0        
        //   202: iload_3        
        //   203: bipush          58
        //   205: invokestatic    uiztfzghuzt/zf.a:(Ljava/lang/String;IC)Z
        //   208: iload           18
        //   210: ifne            241
        //   213: ifeq            223
        //   216: goto            220
        //   219: athrow         
        //   220: iinc            3, 1
        //   223: aload_0        
        //   224: iload_3        
        //   225: iinc            3, 2
        //   228: iload_3        
        //   229: invokestatic    uiztfzghuzt/zf.a:(Ljava/lang/String;II)I
        //   232: istore          8
        //   234: aload_0        
        //   235: iload_3        
        //   236: bipush          58
        //   238: invokestatic    uiztfzghuzt/zf.a:(Ljava/lang/String;IC)Z
        //   241: iload           18
        //   243: ifne            260
        //   246: ifeq            256
        //   249: goto            253
        //   252: athrow         
        //   253: iinc            3, 1
        //   256: aload_0        
        //   257: invokevirtual   java/lang/String.length:()I
        //   260: iload_3        
        //   261: iload           18
        //   263: ifne            532
        //   266: if_icmple       527
        //   269: goto            273
        //   272: athrow         
        //   273: aload_0        
        //   274: iload_3        
        //   275: invokevirtual   java/lang/String.charAt:(I)C
        //   278: istore          12
        //   280: iload           12
        //   282: bipush          90
        //   284: iload           18
        //   286: ifne            532
        //   289: if_icmpeq       527
        //   292: goto            296
        //   295: athrow         
        //   296: iload           12
        //   298: bipush          43
        //   300: iload           18
        //   302: ifne            532
        //   305: goto            309
        //   308: athrow         
        //   309: if_icmpeq       527
        //   312: goto            316
        //   315: athrow         
        //   316: iload           12
        //   318: bipush          45
        //   320: iload           18
        //   322: ifne            532
        //   325: goto            329
        //   328: athrow         
        //   329: if_icmpeq       527
        //   332: goto            336
        //   335: athrow         
        //   336: aload_0        
        //   337: iload_3        
        //   338: iinc            3, 2
        //   341: iload_3        
        //   342: invokestatic    uiztfzghuzt/zf.a:(Ljava/lang/String;II)I
        //   345: istore          9
        //   347: iload           9
        //   349: iload           18
        //   351: ifne            394
        //   354: bipush          59
        //   356: if_icmple       387
        //   359: goto            363
        //   362: athrow         
        //   363: iload           9
        //   365: iload           18
        //   367: ifne            394
        //   370: goto            374
        //   373: athrow         
        //   374: bipush          63
        //   376: if_icmpge       387
        //   379: goto            383
        //   382: athrow         
        //   383: bipush          59
        //   385: istore          9
        //   387: aload_0        
        //   388: iload_3        
        //   389: bipush          46
        //   391: invokestatic    uiztfzghuzt/zf.a:(Ljava/lang/String;IC)Z
        //   394: iload           18
        //   396: ifne            531
        //   399: ifeq            527
        //   402: goto            406
        //   405: athrow         
        //   406: iinc            3, 1
        //   409: aload_0        
        //   410: iload_3        
        //   411: iconst_1       
        //   412: iadd           
        //   413: invokestatic    uiztfzghuzt/zf.a:(Ljava/lang/String;I)I
        //   416: istore          13
        //   418: iload           13
        //   420: iload_3        
        //   421: iconst_3       
        //   422: iadd           
        //   423: invokestatic    java/lang/Math.min:(II)I
        //   426: istore          14
        //   428: aload_0        
        //   429: iload_3        
        //   430: iload           14
        //   432: invokestatic    uiztfzghuzt/zf.a:(Ljava/lang/String;II)I
        //   435: istore          15
        //   437: iload           14
        //   439: iload_3        
        //   440: isub           
        //   441: iload           18
        //   443: ifne            522
        //   446: lookupswitch {
        //                1: 504
        //                2: 473
        //          default: 516
        //        }
        //   472: athrow         
        //   473: iload           15
        //   475: bipush          10
        //   477: imul           
        //   478: istore          10
        //   480: iload           18
        //   482: ifeq            524
        //   485: getstatic       uiztfzghuzt/nb.a:Z
        //   488: ifeq            500
        //   491: goto            495
        //   494: athrow         
        //   495: iconst_0       
        //   496: goto            501
        //   499: athrow         
        //   500: iconst_1       
        //   501: putstatic       uiztfzghuzt/nb.a:Z
        //   504: iload           15
        //   506: bipush          100
        //   508: imul           
        //   509: istore          10
        //   511: iload           18
        //   513: ifeq            524
        //   516: iload           15
        //   518: goto            522
        //   521: athrow         
        //   522: istore          10
        //   524: iload           13
        //   526: istore_3       
        //   527: aload_0        
        //   528: invokevirtual   java/lang/String.length:()I
        //   531: iload_3        
        //   532: if_icmpgt       546
        //   535: new             Ljava/lang/IllegalArgumentException;
        //   538: dup            
        //   539: ldc             "No time zone indicator"
        //   541: invokespecial   java/lang/IllegalArgumentException.<init>:(Ljava/lang/String;)V
        //   544: athrow         
        //   545: athrow         
        //   546: aconst_null    
        //   547: astore          12
        //   549: aload_0        
        //   550: iload_3        
        //   551: invokevirtual   java/lang/String.charAt:(I)C
        //   554: istore          13
        //   556: iload           13
        //   558: bipush          90
        //   560: iload           18
        //   562: ifne            587
        //   565: if_icmpne       583
        //   568: goto            572
        //   571: athrow         
        //   572: getstatic       uiztfzghuzt/zf.a:Ljava/util/TimeZone;
        //   575: astore          12
        //   577: iinc            3, 1
        //   580: goto            882
        //   583: iload           13
        //   585: bipush          43
        //   587: iload           18
        //   589: ifne            607
        //   592: if_icmpeq       610
        //   595: goto            599
        //   598: athrow         
        //   599: iload           13
        //   601: bipush          45
        //   603: goto            607
        //   606: athrow         
        //   607: if_icmpne       849
        //   610: aload_0        
        //   611: iload_3        
        //   612: invokevirtual   java/lang/String.substring:(I)Ljava/lang/String;
        //   615: astore          14
        //   617: aload           14
        //   619: iload           18
        //   621: ifne            641
        //   624: invokevirtual   java/lang/String.length:()I
        //   627: iconst_5       
        //   628: if_icmplt       644
        //   631: goto            635
        //   634: athrow         
        //   635: aload           14
        //   637: goto            641
        //   640: athrow         
        //   641: goto            664
        //   644: new             Ljava/lang/StringBuilder;
        //   647: dup            
        //   648: invokespecial   java/lang/StringBuilder.<init>:()V
        //   651: aload           14
        //   653: invokevirtual   java/lang/StringBuilder.append:(Ljava/lang/String;)Ljava/lang/StringBuilder;
        //   656: ldc             "00"
        //   658: invokevirtual   java/lang/StringBuilder.append:(Ljava/lang/String;)Ljava/lang/StringBuilder;
        //   661: invokevirtual   java/lang/StringBuilder.toString:()Ljava/lang/String;
        //   664: astore          14
        //   666: iload_3        
        //   667: aload           14
        //   669: invokevirtual   java/lang/String.length:()I
        //   672: iadd           
        //   673: istore_3       
        //   674: ldc             "+0000"
        //   676: aload           14
        //   678: invokevirtual   java/lang/String.equals:(Ljava/lang/Object;)Z
        //   681: iload           18
        //   683: ifne            713
        //   686: ifne            716
        //   689: goto            693
        //   692: athrow         
        //   693: ldc             "+00:00"
        //   695: iload           18
        //   697: ifne            744
        //   700: goto            704
        //   703: athrow         
        //   704: aload           14
        //   706: invokevirtual   java/lang/String.equals:(Ljava/lang/Object;)Z
        //   709: goto            713
        //   712: athrow         
        //   713: ifeq            724
        //   716: getstatic       uiztfzghuzt/zf.a:Ljava/util/TimeZone;
        //   719: astore          12
        //   721: goto            846
        //   724: new             Ljava/lang/StringBuilder;
        //   727: dup            
        //   728: invokespecial   java/lang/StringBuilder.<init>:()V
        //   731: ldc             "GMT"
        //   733: invokevirtual   java/lang/StringBuilder.append:(Ljava/lang/String;)Ljava/lang/StringBuilder;
        //   736: aload           14
        //   738: invokevirtual   java/lang/StringBuilder.append:(Ljava/lang/String;)Ljava/lang/StringBuilder;
        //   741: invokevirtual   java/lang/StringBuilder.toString:()Ljava/lang/String;
        //   744: astore          15
        //   746: aload           15
        //   748: invokestatic    java/util/TimeZone.getTimeZone:(Ljava/lang/String;)Ljava/util/TimeZone;
        //   751: astore          12
        //   753: aload           12
        //   755: invokevirtual   java/util/TimeZone.getID:()Ljava/lang/String;
        //   758: astore          16
        //   760: aload           16
        //   762: aload           15
        //   764: iload           18
        //   766: ifne            787
        //   769: invokevirtual   java/lang/String.equals:(Ljava/lang/Object;)Z
        //   772: ifne            846
        //   775: goto            779
        //   778: athrow         
        //   779: aload           16
        //   781: ldc             ":"
        //   783: goto            787
        //   786: athrow         
        //   787: ldc             ""
        //   789: invokevirtual   java/lang/String.replace:(Ljava/lang/CharSequence;Ljava/lang/CharSequence;)Ljava/lang/String;
        //   792: astore          17
        //   794: aload           17
        //   796: aload           15
        //   798: invokevirtual   java/lang/String.equals:(Ljava/lang/Object;)Z
        //   801: ifne            846
        //   804: new             Ljava/lang/IndexOutOfBoundsException;
        //   807: dup            
        //   808: new             Ljava/lang/StringBuilder;
        //   811: dup            
        //   812: invokespecial   java/lang/StringBuilder.<init>:()V
        //   815: ldc             "Mismatching time zone indicator: "
        //   817: invokevirtual   java/lang/StringBuilder.append:(Ljava/lang/String;)Ljava/lang/StringBuilder;
        //   820: aload           15
        //   822: invokevirtual   java/lang/StringBuilder.append:(Ljava/lang/String;)Ljava/lang/StringBuilder;
        //   825: ldc             " given, resolves to "
        //   827: invokevirtual   java/lang/StringBuilder.append:(Ljava/lang/String;)Ljava/lang/StringBuilder;
        //   830: aload           12
        //   832: invokevirtual   java/util/TimeZone.getID:()Ljava/lang/String;
        //   835: invokevirtual   java/lang/StringBuilder.append:(Ljava/lang/String;)Ljava/lang/StringBuilder;
        //   838: invokevirtual   java/lang/StringBuilder.toString:()Ljava/lang/String;
        //   841: invokespecial   java/lang/IndexOutOfBoundsException.<init>:(Ljava/lang/String;)V
        //   844: athrow         
        //   845: athrow         
        //   846: goto            882
        //   849: new             Ljava/lang/IndexOutOfBoundsException;
        //   852: dup            
        //   853: new             Ljava/lang/StringBuilder;
        //   856: dup            
        //   857: invokespecial   java/lang/StringBuilder.<init>:()V
        //   860: ldc             "Invalid time zone indicator '"
        //   862: invokevirtual   java/lang/StringBuilder.append:(Ljava/lang/String;)Ljava/lang/StringBuilder;
        //   865: iload           13
        //   867: invokevirtual   java/lang/StringBuilder.append:(C)Ljava/lang/StringBuilder;
        //   870: ldc             "'"
        //   872: invokevirtual   java/lang/StringBuilder.append:(Ljava/lang/String;)Ljava/lang/StringBuilder;
        //   875: invokevirtual   java/lang/StringBuilder.toString:()Ljava/lang/String;
        //   878: invokespecial   java/lang/IndexOutOfBoundsException.<init>:(Ljava/lang/String;)V
        //   881: athrow         
        //   882: new             Ljava/util/GregorianCalendar;
        //   885: dup            
        //   886: aload           12
        //   888: invokespecial   java/util/GregorianCalendar.<init>:(Ljava/util/TimeZone;)V
        //   891: astore          14
        //   893: aload           14
        //   895: iconst_0       
        //   896: invokevirtual   java/util/Calendar.setLenient:(Z)V
        //   899: aload           14
        //   901: iconst_1       
        //   902: iload           4
        //   904: invokevirtual   java/util/Calendar.set:(II)V
        //   907: aload           14
        //   909: iconst_2       
        //   910: iload           5
        //   912: iconst_1       
        //   913: isub           
        //   914: invokevirtual   java/util/Calendar.set:(II)V
        //   917: aload           14
        //   919: iconst_5       
        //   920: iload           6
        //   922: invokevirtual   java/util/Calendar.set:(II)V
        //   925: aload           14
        //   927: bipush          11
        //   929: iload           7
        //   931: invokevirtual   java/util/Calendar.set:(II)V
        //   934: aload           14
        //   936: bipush          12
        //   938: iload           8
        //   940: invokevirtual   java/util/Calendar.set:(II)V
        //   943: aload           14
        //   945: bipush          13
        //   947: iload           9
        //   949: invokevirtual   java/util/Calendar.set:(II)V
        //   952: aload           14
        //   954: bipush          14
        //   956: iload           10
        //   958: invokevirtual   java/util/Calendar.set:(II)V
        //   961: aload_1        
        //   962: iload_3        
        //   963: invokevirtual   java/text/ParsePosition.setIndex:(I)V
        //   966: aload           14
        //   968: invokevirtual   java/util/Calendar.getTime:()Ljava/util/Date;
        //   971: areturn        
        //   972: astore_3       
        //   973: aload_3        
        //   974: astore_2       
        //   975: goto            987
        //   978: astore_3       
        //   979: aload_3        
        //   980: astore_2       
        //   981: goto            987
        //   984: astore_3       
        //   985: aload_3        
        //   986: astore_2       
        //   987: aload_0        
        //   988: ifnonnull       996
        //   991: aconst_null    
        //   992: goto            1020
        //   995: athrow         
        //   996: new             Ljava/lang/StringBuilder;
        //   999: dup            
        //  1000: invokespecial   java/lang/StringBuilder.<init>:()V
        //  1003: bipush          34
        //  1005: invokevirtual   java/lang/StringBuilder.append:(C)Ljava/lang/StringBuilder;
        //  1008: aload_0        
        //  1009: invokevirtual   java/lang/StringBuilder.append:(Ljava/lang/String;)Ljava/lang/StringBuilder;
        //  1012: ldc             "'"
        //  1014: invokevirtual   java/lang/StringBuilder.append:(Ljava/lang/String;)Ljava/lang/StringBuilder;
        //  1017: invokevirtual   java/lang/StringBuilder.toString:()Ljava/lang/String;
        //  1020: astore_3       
        //  1021: aload_2        
        //  1022: invokevirtual   java/lang/Exception.getMessage:()Ljava/lang/String;
        //  1025: astore          4
        //  1027: aload           4
        //  1029: iload           18
        //  1031: ifne            1096
        //  1034: ifnull          1062
        //  1037: goto            1041
        //  1040: athrow         
        //  1041: aload           4
        //  1043: iload           18
        //  1045: ifne            1096
        //  1048: goto            1052
        //  1051: athrow         
        //  1052: invokevirtual   java/lang/String.isEmpty:()Z
        //  1055: ifeq            1098
        //  1058: goto            1062
        //  1061: athrow         
        //  1062: new             Ljava/lang/StringBuilder;
        //  1065: dup            
        //  1066: invokespecial   java/lang/StringBuilder.<init>:()V
        //  1069: ldc             "("
        //  1071: invokevirtual   java/lang/StringBuilder.append:(Ljava/lang/String;)Ljava/lang/StringBuilder;
        //  1074: aload_2        
        //  1075: invokevirtual   java/lang/Object.getClass:()Ljava/lang/Class;
        //  1078: invokevirtual   java/lang/Class.getName:()Ljava/lang/String;
        //  1081: invokevirtual   java/lang/StringBuilder.append:(Ljava/lang/String;)Ljava/lang/StringBuilder;
        //  1084: ldc             ")"
        //  1086: invokevirtual   java/lang/StringBuilder.append:(Ljava/lang/String;)Ljava/lang/StringBuilder;
        //  1089: invokevirtual   java/lang/StringBuilder.toString:()Ljava/lang/String;
        //  1092: goto            1096
        //  1095: athrow         
        //  1096: astore          4
        //  1098: new             Ljava/text/ParseException;
        //  1101: dup            
        //  1102: new             Ljava/lang/StringBuilder;
        //  1105: dup            
        //  1106: invokespecial   java/lang/StringBuilder.<init>:()V
        //  1109: ldc             "Failed to parse date ["
        //  1111: invokevirtual   java/lang/StringBuilder.append:(Ljava/lang/String;)Ljava/lang/StringBuilder;
        //  1114: aload_3        
        //  1115: invokevirtual   java/lang/StringBuilder.append:(Ljava/lang/String;)Ljava/lang/StringBuilder;
        //  1118: ldc             "]: "
        //  1120: invokevirtual   java/lang/StringBuilder.append:(Ljava/lang/String;)Ljava/lang/StringBuilder;
        //  1123: aload           4
        //  1125: invokevirtual   java/lang/StringBuilder.append:(Ljava/lang/String;)Ljava/lang/StringBuilder;
        //  1128: invokevirtual   java/lang/StringBuilder.toString:()Ljava/lang/String;
        //  1131: aload_1        
        //  1132: invokevirtual   java/text/ParsePosition.getIndex:()I
        //  1135: invokespecial   java/text/ParseException.<init>:(Ljava/lang/String;I)V
        //  1138: astore          5
        //  1140: aload           5
        //  1142: aload_2        
        //  1143: invokevirtual   java/text/ParseException.initCause:(Ljava/lang/Throwable;)Ljava/lang/Throwable;
        //  1146: pop            
        //  1147: aload           5
        //  1149: athrow         
        //    StackMapTable: 00 71 FF 00 29 00 13 07 00 21 07 00 15 05 01 01 00 00 00 00 00 00 00 00 00 00 00 00 00 01 00 01 07 00 0D 00 02 48 01 FF 00 13 00 13 07 00 21 07 00 15 05 01 01 01 00 00 00 00 00 00 00 00 00 00 00 00 01 00 01 07 00 0D 00 02 48 01 FF 00 23 00 13 07 00 21 07 00 15 05 01 01 01 01 01 01 01 01 01 00 00 00 00 00 00 01 00 01 07 00 0D 00 4B 07 00 0D 40 01 46 07 00 0D 00 1B 41 01 4A 07 00 0D 00 5F 07 00 0D 00 02 51 01 4A 07 00 0D 00 02 43 01 4B 07 00 0D 00 FF 00 15 00 13 07 00 21 07 00 15 05 01 01 01 01 01 01 01 01 01 01 00 00 00 00 00 01 00 01 07 00 0D 00 4B 07 00 0D FF 00 00 00 13 07 00 21 07 00 15 05 01 01 01 01 01 01 01 01 01 01 00 00 00 00 00 01 00 02 01 01 45 07 00 0D 00 4B 07 00 0D FF 00 00 00 13 07 00 21 07 00 15 05 01 01 01 01 01 01 01 01 01 01 00 00 00 00 00 01 00 02 01 01 45 07 00 0D 00 59 07 00 0D 00 49 07 00 0D 40 01 47 07 00 0D 00 03 46 01 4A 07 00 0D 00 FF 00 41 00 13 07 00 21 07 00 15 05 01 01 01 01 01 01 01 01 01 01 01 01 01 00 00 01 00 01 07 00 0D 00 54 07 00 0D 00 43 07 00 0D 00 40 01 02 0B 44 07 00 0D 40 01 01 FF 00 02 00 13 07 00 21 07 00 15 05 01 01 01 01 01 01 01 01 01 00 00 00 00 00 00 01 00 00 43 01 FF 00 00 00 13 07 00 21 07 00 15 05 01 01 01 01 01 01 01 01 01 00 00 00 00 00 00 01 00 02 01 01 4C 07 00 0D 00 FF 00 18 00 13 07 00 21 07 00 15 05 01 01 01 01 01 01 01 01 01 05 01 00 00 00 00 01 00 01 07 00 0D 00 0A FF 00 03 00 13 07 00 21 07 00 15 05 01 01 01 01 01 01 01 01 01 05 01 00 00 00 00 01 00 02 01 01 4A 07 00 0D 00 46 07 00 0D FF 00 00 00 13 07 00 21 07 00 15 05 01 01 01 01 01 01 01 01 01 05 01 00 00 00 00 01 00 02 01 01 02 FF 00 17 00 13 07 00 21 07 00 15 05 01 01 01 01 01 01 01 01 01 05 01 07 00 21 00 00 00 01 00 01 07 00 0D 00 44 07 00 0D 40 07 00 21 02 53 07 00 21 5B 07 00 0D 00 49 07 00 0D 40 07 00 21 47 07 00 0D 40 01 02 07 53 07 00 21 FF 00 21 00 13 07 00 21 07 00 15 05 01 01 01 01 01 01 01 01 01 07 00 6B 01 07 00 21 07 00 21 07 00 21 00 01 00 01 07 00 0D 00 46 07 00 0D FF 00 00 00 13 07 00 21 07 00 15 05 01 01 01 01 01 01 01 01 01 07 00 6B 01 07 00 21 07 00 21 07 00 21 00 01 00 02 07 00 21 07 00 21 FF 00 39 00 13 07 00 21 07 00 15 05 01 01 01 01 01 01 01 01 01 07 00 6B 01 07 00 21 07 00 21 07 00 21 07 00 21 01 00 01 07 00 0D FF 00 00 00 13 07 00 21 07 00 15 05 01 01 01 01 01 01 01 01 01 07 00 6B 01 07 00 21 00 00 00 01 00 00 FF 00 02 00 13 07 00 21 07 00 15 05 01 01 01 01 01 01 01 01 01 05 01 00 00 00 00 01 00 00 FF 00 20 00 13 07 00 21 07 00 15 05 01 01 01 01 01 01 01 01 01 07 00 6B 01 00 00 00 00 01 00 00 FF 00 59 00 13 07 00 21 07 00 15 05 00 00 00 00 00 00 00 00 00 00 00 00 00 00 00 01 00 01 07 00 0D 45 07 00 0F 45 07 00 11 FF 00 02 00 13 07 00 21 07 00 15 07 00 B6 07 00 B6 00 00 00 00 00 00 00 00 00 00 00 00 00 00 01 00 00 47 07 00 0D 00 57 07 00 21 FF 00 13 00 13 07 00 21 07 00 15 07 00 B6 07 00 21 07 00 21 00 00 00 00 00 00 00 00 00 00 00 00 00 01 00 01 07 00 0D 00 49 07 00 0D 40 07 00 21 48 07 00 0D 00 60 07 00 0D 40 07 00 21 01
        //    Exceptions:
        //  Try           Handler
        //  Start  End    Start  End    Type                                 
        //  -----  -----  -----  -----  -------------------------------------
        //  124    141    144    145    Ljava/lang/IndexOutOfBoundsException;
        //  117    133    136    137    Ljava/lang/IndexOutOfBoundsException;
        //  110    120    123    124    Ljava/lang/IndexOutOfBoundsException;
        //  56     71     74     75     Ljava/lang/IndexOutOfBoundsException;
        //  23     38     41     42     Ljava/lang/IndexOutOfBoundsException;
        //  7      172    972    978    Ljava/lang/IndexOutOfBoundsException;
        //  173    971    972    978    Ljava/lang/IndexOutOfBoundsException;
        //  7      172    978    984    Ljava/lang/NumberFormatException;
        //  173    971    978    984    Ljava/lang/NumberFormatException;
        //  7      172    984    987    Ljava/lang/IllegalArgumentException;
        //  794    845    845    846    Ljava/lang/IndexOutOfBoundsException;
        //  769    783    786    787    Ljava/lang/IndexOutOfBoundsException;
        //  760    775    778    779    Ljava/lang/IndexOutOfBoundsException;
        //  693    709    712    713    Ljava/lang/IndexOutOfBoundsException;
        //  686    700    703    704    Ljava/lang/IndexOutOfBoundsException;
        //  674    689    692    693    Ljava/lang/IndexOutOfBoundsException;
        //  624    637    640    641    Ljava/lang/IndexOutOfBoundsException;
        //  617    631    634    635    Ljava/lang/IndexOutOfBoundsException;
        //  592    603    606    607    Ljava/lang/IndexOutOfBoundsException;
        //  587    595    598    599    Ljava/lang/IndexOutOfBoundsException;
        //  556    568    571    572    Ljava/lang/IndexOutOfBoundsException;
        //  532    545    545    546    Ljava/lang/IndexOutOfBoundsException;
        //  511    518    521    522    Ljava/lang/IndexOutOfBoundsException;
        //  485    499    499    500    Ljava/lang/IndexOutOfBoundsException;
        //  480    491    494    495    Ljava/lang/IndexOutOfBoundsException;
        //  437    472    472    473    Ljava/lang/IndexOutOfBoundsException;
        //  394    402    405    406    Ljava/lang/IndexOutOfBoundsException;
        //  363    379    382    383    Ljava/lang/IndexOutOfBoundsException;
        //  354    370    373    374    Ljava/lang/IndexOutOfBoundsException;
        //  347    359    362    363    Ljava/lang/IndexOutOfBoundsException;
        //  316    332    335    336    Ljava/lang/IndexOutOfBoundsException;
        //  309    325    328    329    Ljava/lang/IndexOutOfBoundsException;
        //  296    312    315    316    Ljava/lang/IndexOutOfBoundsException;
        //  289    305    308    309    Ljava/lang/IndexOutOfBoundsException;
        //  280    292    295    296    Ljava/lang/IndexOutOfBoundsException;
        //  260    269    272    273    Ljava/lang/IndexOutOfBoundsException;
        //  241    249    252    253    Ljava/lang/IndexOutOfBoundsException;
        //  201    216    219    220    Ljava/lang/IndexOutOfBoundsException;
        //  175    183    186    187    Ljava/lang/IndexOutOfBoundsException;
        //  173    971    984    987    Ljava/lang/IllegalArgumentException;
        //  1052   1092   1095   1096   Ljava/lang/IndexOutOfBoundsException;
        //  1041   1058   1061   1062   Ljava/lang/IndexOutOfBoundsException;
        //  1034   1048   1051   1052   Ljava/lang/IndexOutOfBoundsException;
        //  1027   1037   1040   1041   Ljava/lang/IndexOutOfBoundsException;
        //  987    995    995    996    Ljava/lang/IndexOutOfBoundsException;
        // 
        // The error that occurred was:
        // 
        // java.lang.IllegalStateException: Expression is linked from several locations: Label_0124:
        //     at com.strobel.decompiler.ast.Error.expressionLinkedFromMultipleLocations(Error.java:27)
        //     at com.strobel.decompiler.ast.AstOptimizer.mergeDisparateObjectInitializations(AstOptimizer.java:2596)
        //     at com.strobel.decompiler.ast.AstOptimizer.optimize(AstOptimizer.java:235)
        //     at com.strobel.decompiler.ast.AstOptimizer.optimize(AstOptimizer.java:42)
        //     at com.strobel.decompiler.languages.java.ast.AstMethodBodyBuilder.createMethodBody(AstMethodBodyBuilder.java:214)
        //     at com.strobel.decompiler.languages.java.ast.AstMethodBodyBuilder.createMethodBody(AstMethodBodyBuilder.java:99)
        //     at com.strobel.decompiler.languages.java.ast.AstBuilder.createMethodBody(AstBuilder.java:782)
        //     at com.strobel.decompiler.languages.java.ast.AstBuilder.createMethod(AstBuilder.java:675)
        //     at com.strobel.decompiler.languages.java.ast.AstBuilder.addTypeMembers(AstBuilder.java:552)
        //     at com.strobel.decompiler.languages.java.ast.AstBuilder.createTypeCore(AstBuilder.java:519)
        //     at com.strobel.decompiler.languages.java.ast.AstBuilder.createTypeNoCache(AstBuilder.java:161)
        //     at com.strobel.decompiler.languages.java.ast.AstBuilder.createType(AstBuilder.java:150)
        //     at com.strobel.decompiler.languages.java.ast.AstBuilder.addType(AstBuilder.java:125)
        //     at com.strobel.decompiler.languages.java.JavaLanguage.buildAst(JavaLanguage.java:71)
        //     at com.strobel.decompiler.languages.java.JavaLanguage.decompileType(JavaLanguage.java:59)
        //     at com.strobel.decompiler.DecompilerDriver.decompileType(DecompilerDriver.java:330)
        //     at com.strobel.decompiler.DecompilerDriver.decompileJar(DecompilerDriver.java:251)
        //     at com.strobel.decompiler.DecompilerDriver.main(DecompilerDriver.java:126)
        // 
        throw new IllegalStateException("An error occurred while decompiling this method.");
    }
    
    private static boolean a(final String p0, final int p1, final char p2) {
        // 
        // This method could not be decompiled.
        // 
        // Original Bytecode:
        // 
        //     3: istore_3       
        //     4: iload_1        
        //     5: aload_0        
        //     6: invokevirtual   java/lang/String.length:()I
        //     9: iload_3        
        //    10: ifne            38
        //    13: if_icmpge       45
        //    16: goto            20
        //    19: athrow         
        //    20: aload_0        
        //    21: iload_1        
        //    22: invokevirtual   java/lang/String.charAt:(I)C
        //    25: iload_3        
        //    26: ifne            42
        //    29: goto            33
        //    32: athrow         
        //    33: iload_2        
        //    34: goto            38
        //    37: athrow         
        //    38: if_icmpne       45
        //    41: iconst_1       
        //    42: goto            46
        //    45: iconst_0       
        //    46: ireturn        
        //    StackMapTable: 00 09 FF 00 13 00 04 07 00 21 01 01 01 00 01 07 00 11 00 4B 07 00 11 40 01 43 07 00 11 FF 00 00 00 04 07 00 21 01 01 01 00 02 01 01 43 01 02 40 01
        //    Exceptions:
        //  Try           Handler
        //  Start  End    Start  End    Type                                
        //  -----  -----  -----  -----  ------------------------------------
        //  20     34     37     38     Ljava/lang/IllegalArgumentException;
        //  13     29     32     33     Ljava/lang/IllegalArgumentException;
        //  4      16     19     20     Ljava/lang/IllegalArgumentException;
        // 
        // The error that occurred was:
        // 
        // java.lang.IllegalStateException: Expression is linked from several locations: Label_0020:
        //     at com.strobel.decompiler.ast.Error.expressionLinkedFromMultipleLocations(Error.java:27)
        //     at com.strobel.decompiler.ast.AstOptimizer.mergeDisparateObjectInitializations(AstOptimizer.java:2596)
        //     at com.strobel.decompiler.ast.AstOptimizer.optimize(AstOptimizer.java:235)
        //     at com.strobel.decompiler.ast.AstOptimizer.optimize(AstOptimizer.java:42)
        //     at com.strobel.decompiler.languages.java.ast.AstMethodBodyBuilder.createMethodBody(AstMethodBodyBuilder.java:214)
        //     at com.strobel.decompiler.languages.java.ast.AstMethodBodyBuilder.createMethodBody(AstMethodBodyBuilder.java:99)
        //     at com.strobel.decompiler.languages.java.ast.AstBuilder.createMethodBody(AstBuilder.java:782)
        //     at com.strobel.decompiler.languages.java.ast.AstBuilder.createMethod(AstBuilder.java:675)
        //     at com.strobel.decompiler.languages.java.ast.AstBuilder.addTypeMembers(AstBuilder.java:552)
        //     at com.strobel.decompiler.languages.java.ast.AstBuilder.createTypeCore(AstBuilder.java:519)
        //     at com.strobel.decompiler.languages.java.ast.AstBuilder.createTypeNoCache(AstBuilder.java:161)
        //     at com.strobel.decompiler.languages.java.ast.AstBuilder.createType(AstBuilder.java:150)
        //     at com.strobel.decompiler.languages.java.ast.AstBuilder.addType(AstBuilder.java:125)
        //     at com.strobel.decompiler.languages.java.JavaLanguage.buildAst(JavaLanguage.java:71)
        //     at com.strobel.decompiler.languages.java.JavaLanguage.decompileType(JavaLanguage.java:59)
        //     at com.strobel.decompiler.DecompilerDriver.decompileType(DecompilerDriver.java:330)
        //     at com.strobel.decompiler.DecompilerDriver.decompileJar(DecompilerDriver.java:251)
        //     at com.strobel.decompiler.DecompilerDriver.main(DecompilerDriver.java:126)
        // 
        throw new IllegalStateException("An error occurred while decompiling this method.");
    }
    
    private static int a(final String p0, final int p1, final int p2) {
        // 
        // This method could not be decompiled.
        // 
        // Original Bytecode:
        // 
        //     3: istore          6
        //     5: iload_1        
        //     6: iload           6
        //     8: ifne            19
        //    11: iflt            53
        //    14: goto            18
        //    17: athrow         
        //    18: iload_2        
        //    19: aload_0        
        //    20: invokevirtual   java/lang/String.length:()I
        //    23: iload           6
        //    25: ifne            50
        //    28: if_icmpgt       53
        //    31: goto            35
        //    34: athrow         
        //    35: iload_1        
        //    36: iload           6
        //    38: ifne            64
        //    41: goto            45
        //    44: athrow         
        //    45: iload_2        
        //    46: goto            50
        //    49: athrow         
        //    50: if_icmple       63
        //    53: new             Ljava/lang/NumberFormatException;
        //    56: dup            
        //    57: aload_0        
        //    58: invokespecial   java/lang/NumberFormatException.<init>:(Ljava/lang/String;)V
        //    61: athrow         
        //    62: athrow         
        //    63: iload_1        
        //    64: istore_3       
        //    65: iconst_0       
        //    66: istore          4
        //    68: iload_3        
        //    69: iload_2        
        //    70: iload           6
        //    72: ifne            151
        //    75: if_icmpge       149
        //    78: goto            82
        //    81: athrow         
        //    82: aload_0        
        //    83: iload_3        
        //    84: iinc            3, 1
        //    87: invokevirtual   java/lang/String.charAt:(I)C
        //    90: bipush          10
        //    92: invokestatic    java/lang/Character.digit:(CI)I
        //    95: istore          5
        //    97: iload           5
        //    99: iload           6
        //   101: ifne            147
        //   104: ifge            144
        //   107: goto            111
        //   110: athrow         
        //   111: new             Ljava/lang/NumberFormatException;
        //   114: dup            
        //   115: new             Ljava/lang/StringBuilder;
        //   118: dup            
        //   119: invokespecial   java/lang/StringBuilder.<init>:()V
        //   122: ldc             "Invalid number: "
        //   124: invokevirtual   java/lang/StringBuilder.append:(Ljava/lang/String;)Ljava/lang/StringBuilder;
        //   127: aload_0        
        //   128: iload_1        
        //   129: iload_2        
        //   130: invokevirtual   java/lang/String.substring:(II)Ljava/lang/String;
        //   133: invokevirtual   java/lang/StringBuilder.append:(Ljava/lang/String;)Ljava/lang/StringBuilder;
        //   136: invokevirtual   java/lang/StringBuilder.toString:()Ljava/lang/String;
        //   139: invokespecial   java/lang/NumberFormatException.<init>:(Ljava/lang/String;)V
        //   142: athrow         
        //   143: athrow         
        //   144: iload           5
        //   146: ineg           
        //   147: istore          4
        //   149: iload_3        
        //   150: iload_2        
        //   151: if_icmpge       244
        //   154: aload_0        
        //   155: iload_3        
        //   156: iinc            3, 1
        //   159: invokevirtual   java/lang/String.charAt:(I)C
        //   162: bipush          10
        //   164: invokestatic    java/lang/Character.digit:(CI)I
        //   167: istore          5
        //   169: iload           5
        //   171: iload           6
        //   173: ifne            247
        //   176: iload           6
        //   178: ifne            237
        //   181: goto            185
        //   184: athrow         
        //   185: ifge            225
        //   188: goto            192
        //   191: athrow         
        //   192: new             Ljava/lang/NumberFormatException;
        //   195: dup            
        //   196: new             Ljava/lang/StringBuilder;
        //   199: dup            
        //   200: invokespecial   java/lang/StringBuilder.<init>:()V
        //   203: ldc             "Invalid number: "
        //   205: invokevirtual   java/lang/StringBuilder.append:(Ljava/lang/String;)Ljava/lang/StringBuilder;
        //   208: aload_0        
        //   209: iload_1        
        //   210: iload_2        
        //   211: invokevirtual   java/lang/String.substring:(II)Ljava/lang/String;
        //   214: invokevirtual   java/lang/StringBuilder.append:(Ljava/lang/String;)Ljava/lang/StringBuilder;
        //   217: invokevirtual   java/lang/StringBuilder.toString:()Ljava/lang/String;
        //   220: invokespecial   java/lang/NumberFormatException.<init>:(Ljava/lang/String;)V
        //   223: athrow         
        //   224: athrow         
        //   225: iload           4
        //   227: bipush          10
        //   229: imul           
        //   230: istore          4
        //   232: iload           4
        //   234: iload           5
        //   236: isub           
        //   237: istore          4
        //   239: iload           6
        //   241: ifeq            149
        //   244: iload           4
        //   246: ineg           
        //   247: ireturn        
        //    StackMapTable: 00 1F FF 00 11 00 07 07 00 21 01 01 00 00 00 01 00 01 07 00 11 00 40 01 4E 07 00 11 00 48 07 00 11 40 01 43 07 00 11 FF 00 00 00 07 07 00 21 01 01 00 00 00 01 00 02 01 01 02 48 07 00 11 00 40 01 FF 00 10 00 07 07 00 21 01 01 01 01 00 01 00 01 07 00 11 00 FF 00 1B 00 07 07 00 21 01 01 01 01 01 01 00 01 07 00 11 00 5F 07 00 11 00 42 01 FF 00 01 00 07 07 00 21 01 01 01 01 00 01 00 00 FF 00 01 00 07 07 00 21 01 01 01 01 00 01 00 02 01 01 FF 00 20 00 07 07 00 21 01 01 01 01 01 01 00 01 07 00 11 40 01 45 07 00 11 00 5F 07 00 11 00 4B 01 FF 00 06 00 07 07 00 21 01 01 01 01 00 01 00 00 42 01
        //    Exceptions:
        //  Try           Handler
        //  Start  End    Start  End    Type                                
        //  -----  -----  -----  -----  ------------------------------------
        //  185    224    224    225    Ljava/lang/IllegalArgumentException;
        //  176    188    191    192    Ljava/lang/IllegalArgumentException;
        //  169    181    184    185    Ljava/lang/IllegalArgumentException;
        //  104    143    143    144    Ljava/lang/IllegalArgumentException;
        //  97     107    110    111    Ljava/lang/IllegalArgumentException;
        //  68     78     81     82     Ljava/lang/IllegalArgumentException;
        //  50     62     62     63     Ljava/lang/IllegalArgumentException;
        //  35     46     49     50     Ljava/lang/IllegalArgumentException;
        //  28     41     44     45     Ljava/lang/IllegalArgumentException;
        //  19     31     34     35     Ljava/lang/IllegalArgumentException;
        //  5      14     17     18     Ljava/lang/IllegalArgumentException;
        // 
        // The error that occurred was:
        // 
        // java.lang.IllegalStateException: Expression is linked from several locations: Label_0035:
        //     at com.strobel.decompiler.ast.Error.expressionLinkedFromMultipleLocations(Error.java:27)
        //     at com.strobel.decompiler.ast.AstOptimizer.mergeDisparateObjectInitializations(AstOptimizer.java:2596)
        //     at com.strobel.decompiler.ast.AstOptimizer.optimize(AstOptimizer.java:235)
        //     at com.strobel.decompiler.ast.AstOptimizer.optimize(AstOptimizer.java:42)
        //     at com.strobel.decompiler.languages.java.ast.AstMethodBodyBuilder.createMethodBody(AstMethodBodyBuilder.java:214)
        //     at com.strobel.decompiler.languages.java.ast.AstMethodBodyBuilder.createMethodBody(AstMethodBodyBuilder.java:99)
        //     at com.strobel.decompiler.languages.java.ast.AstBuilder.createMethodBody(AstBuilder.java:782)
        //     at com.strobel.decompiler.languages.java.ast.AstBuilder.createMethod(AstBuilder.java:675)
        //     at com.strobel.decompiler.languages.java.ast.AstBuilder.addTypeMembers(AstBuilder.java:552)
        //     at com.strobel.decompiler.languages.java.ast.AstBuilder.createTypeCore(AstBuilder.java:519)
        //     at com.strobel.decompiler.languages.java.ast.AstBuilder.createTypeNoCache(AstBuilder.java:161)
        //     at com.strobel.decompiler.languages.java.ast.AstBuilder.createType(AstBuilder.java:150)
        //     at com.strobel.decompiler.languages.java.ast.AstBuilder.addType(AstBuilder.java:125)
        //     at com.strobel.decompiler.languages.java.JavaLanguage.buildAst(JavaLanguage.java:71)
        //     at com.strobel.decompiler.languages.java.JavaLanguage.decompileType(JavaLanguage.java:59)
        //     at com.strobel.decompiler.DecompilerDriver.decompileType(DecompilerDriver.java:330)
        //     at com.strobel.decompiler.DecompilerDriver.decompileJar(DecompilerDriver.java:251)
        //     at com.strobel.decompiler.DecompilerDriver.main(DecompilerDriver.java:126)
        // 
        throw new IllegalStateException("An error occurred while decompiling this method.");
    }
    
    private static int a(final String p0, final int p1) {
        // 
        // This method could not be decompiled.
        // 
        // Original Bytecode:
        // 
        //     3: istore          4
        //     5: iload_1        
        //     6: istore_2       
        //     7: iload_2        
        //     8: aload_0        
        //     9: invokevirtual   java/lang/String.length:()I
        //    12: if_icmpge       78
        //    15: aload_0        
        //    16: iload_2        
        //    17: invokevirtual   java/lang/String.charAt:(I)C
        //    20: istore_3       
        //    21: iload_3        
        //    22: iload           4
        //    24: ifne            82
        //    27: iload           4
        //    29: ifne            69
        //    32: goto            36
        //    35: athrow         
        //    36: bipush          48
        //    38: if_icmplt       64
        //    41: goto            45
        //    44: athrow         
        //    45: iload_3        
        //    46: iload           4
        //    48: ifne            69
        //    51: goto            55
        //    54: athrow         
        //    55: bipush          57
        //    57: if_icmple       70
        //    60: goto            64
        //    63: athrow         
        //    64: iload_2        
        //    65: goto            69
        //    68: athrow         
        //    69: ireturn        
        //    70: iinc            2, 1
        //    73: iload           4
        //    75: ifeq            7
        //    78: aload_0        
        //    79: invokevirtual   java/lang/String.length:()I
        //    82: ireturn        
        //    StackMapTable: 00 0E FE 00 07 01 00 01 FF 00 1B 00 05 07 00 21 01 01 01 01 00 01 07 00 11 40 01 47 07 00 11 00 48 07 00 11 40 01 47 07 00 11 00 43 07 00 11 40 01 00 FF 00 07 00 05 07 00 21 01 01 00 01 00 00 43 01
        //    Exceptions:
        //  Try           Handler
        //  Start  End    Start  End    Type                                
        //  -----  -----  -----  -----  ------------------------------------
        //  55     65     68     69     Ljava/lang/IllegalArgumentException;
        //  45     60     63     64     Ljava/lang/IllegalArgumentException;
        //  36     51     54     55     Ljava/lang/IllegalArgumentException;
        //  27     41     44     45     Ljava/lang/IllegalArgumentException;
        //  21     32     35     36     Ljava/lang/IllegalArgumentException;
        // 
        // The error that occurred was:
        // 
        // java.lang.IllegalStateException: Expression is linked from several locations: Label_0036:
        //     at com.strobel.decompiler.ast.Error.expressionLinkedFromMultipleLocations(Error.java:27)
        //     at com.strobel.decompiler.ast.AstOptimizer.mergeDisparateObjectInitializations(AstOptimizer.java:2596)
        //     at com.strobel.decompiler.ast.AstOptimizer.optimize(AstOptimizer.java:235)
        //     at com.strobel.decompiler.ast.AstOptimizer.optimize(AstOptimizer.java:42)
        //     at com.strobel.decompiler.languages.java.ast.AstMethodBodyBuilder.createMethodBody(AstMethodBodyBuilder.java:214)
        //     at com.strobel.decompiler.languages.java.ast.AstMethodBodyBuilder.createMethodBody(AstMethodBodyBuilder.java:99)
        //     at com.strobel.decompiler.languages.java.ast.AstBuilder.createMethodBody(AstBuilder.java:782)
        //     at com.strobel.decompiler.languages.java.ast.AstBuilder.createMethod(AstBuilder.java:675)
        //     at com.strobel.decompiler.languages.java.ast.AstBuilder.addTypeMembers(AstBuilder.java:552)
        //     at com.strobel.decompiler.languages.java.ast.AstBuilder.createTypeCore(AstBuilder.java:519)
        //     at com.strobel.decompiler.languages.java.ast.AstBuilder.createTypeNoCache(AstBuilder.java:161)
        //     at com.strobel.decompiler.languages.java.ast.AstBuilder.createType(AstBuilder.java:150)
        //     at com.strobel.decompiler.languages.java.ast.AstBuilder.addType(AstBuilder.java:125)
        //     at com.strobel.decompiler.languages.java.JavaLanguage.buildAst(JavaLanguage.java:71)
        //     at com.strobel.decompiler.languages.java.JavaLanguage.decompileType(JavaLanguage.java:59)
        //     at com.strobel.decompiler.DecompilerDriver.decompileType(DecompilerDriver.java:330)
        //     at com.strobel.decompiler.DecompilerDriver.decompileJar(DecompilerDriver.java:251)
        //     at com.strobel.decompiler.DecompilerDriver.main(DecompilerDriver.java:126)
        // 
        throw new IllegalStateException("An error occurred while decompiling this method.");
    }
    
    static {
        final String[] array = new String[11];
        int n11;
        int n10;
        int n9;
        int n8;
        int n7;
        int n6;
        int n5;
        int n4;
        int n3;
        int n2;
        int n = n2 = (n3 = (n4 = (n5 = (n6 = (n7 = (n8 = (n9 = (n10 = (n11 = 0)))))))));
        String s = "3\f\u001035(";
        int n12 = -1;
        String intern = null;
    Label_0207_Outer:
        while (true) {
            final char[] charArray = s.toCharArray();
            int length;
            int n14;
            final int n13 = n14 = (length = charArray.length);
            int n15 = 0;
            while (true) {
                Label_0281: {
                    if (n13 > 1) {
                        break Label_0281;
                    }
                    length = (n14 = n15);
                    do {
                        final char c = charArray[n14];
                        char c2 = '\0';
                        switch (n15 % 5) {
                            case 0: {
                                c2 = '\u0018';
                                break;
                            }
                            case 1: {
                                c2 = '<';
                                break;
                            }
                            case 2: {
                                c2 = ' ';
                                break;
                            }
                            case 3: {
                                c2 = '\t';
                                break;
                            }
                            default: {
                                c2 = '\u0005';
                                break;
                            }
                        }
                        charArray[length] = (char)(c ^ c2);
                        ++n15;
                    } while (n13 == 0);
                }
                if (n13 > n15) {
                    continue;
                }
                break;
            }
            intern = new String(charArray).intern();
            switch (n12) {
                default: {
                    array[n2] = intern;
                    n = (n2 = (n3 = (n4 = (n5 = (n6 = (n7 = (n8 = (n9 = (n10 = (n11 = 1))))))))));
                    s = "3\f\u001095";
                    n12 = 0;
                    continue Label_0207_Outer;
                }
                case 0: {
                    array[n] = intern;
                    n = (n2 = (n3 = (n4 = (n5 = (n6 = (n7 = (n8 = (n9 = (n10 = (n11 = 2))))))))));
                    s = "UUSddl_H`k\u007f\u001cT`h}\u001cZfk}\u001cIgaq_A}jj\u0006\u0000";
                    n12 = 1;
                    continue Label_0207_Outer;
                }
                case 1: {
                    array[n3] = intern;
                    n = (n2 = (n3 = (n4 = (n5 = (n6 = (n7 = (n8 = (n9 = (n10 = (n11 = 3))))))))));
                    s = "8[I\u007f`v\u0010\u0000{`kSL\u007f`k\u001cTf%";
                    n12 = 2;
                    continue Label_0207_Outer;
                }
                case 2: {
                    array[n4] = intern;
                    n = (n2 = (n3 = (n4 = (n5 = (n6 = (n7 = (n8 = (n9 = (n10 = (n11 = 4))))))))));
                    s = "QRVhiqX\u0000}luY\u0000sjvY\u0000`k|UChqwN\u0000.";
                    n12 = 3;
                    continue Label_0207_Outer;
                }
                case 3: {
                    array[n5] = intern;
                    n = (n2 = (n3 = (n4 = (n5 = (n6 = (n7 = (n8 = (n9 = (n10 = (n11 = 5))))))))));
                    s = "E\u0006\u0000";
                    n12 = 4;
                    continue Label_0207_Outer;
                }
                case 4: {
                    array[n6] = intern;
                    n = (n2 = (n3 = (n4 = (n5 = (n6 = (n7 = (n8 = (n9 = (n10 = (n11 = 6))))))))));
                    s = "_qt";
                    n12 = 5;
                    continue Label_0207_Outer;
                }
                case 5: {
                    array[n7] = intern;
                    n = (n2 = (n3 = (n4 = (n5 = (n6 = (n7 = (n8 = (n9 = (n10 = (n11 = 7))))))))));
                    s = "(\f";
                    n12 = 6;
                    continue Label_0207_Outer;
                }
                case 6: {
                    array[n8] = intern;
                    n = (n2 = (n3 = (n4 = (n5 = (n6 = (n7 = (n8 = (n9 = (n10 = (n11 = 8))))))))));
                    s = "VS\u0000}luY\u0000sjvY\u0000`k|UChqwN";
                    n12 = 7;
                    continue Label_0207_Outer;
                }
                case 7: {
                    array[n9] = intern;
                    n = (n2 = (n3 = (n4 = (n5 = (n6 = (n7 = (n8 = (n9 = (n10 = (n11 = 9))))))))));
                    s = "^]Ie`|\u001cTf%h]Rz`8XA}`8g";
                    n12 = 8;
                    continue Label_0207_Outer;
                }
                case 8: {
                    array[n10] = intern;
                    n = (n2 = (n3 = (n4 = (n5 = (n6 = (n7 = (n8 = (n9 = (n10 = (n11 = 10))))))))));
                    s = "QRVhiqX\u0000gpu^E{?8";
                    n12 = 9;
                    continue Label_0207_Outer;
                }
                case 9: {
                    break Label_0207_Outer;
                }
            }
        }
        array[n11] = intern;
        z = new String[] { "+00:00", "+0000", "Mismatching time zone indicator: ", " given, resolves to ", "Invalid time zone indicator '", "]: ", "GMT", "00", "No time zone indicator", "Failed to parse date [", "Invalid number: " };
        final char[] charArray2 = "Mhc".toCharArray();
        int length2;
        int n17;
        final int n16 = n17 = (length2 = charArray2.length);
        int n18 = 0;
        while (true) {
            Label_0449: {
                if (n16 > 1) {
                    break Label_0449;
                }
                length2 = (n17 = n18);
                do {
                    final char c3 = charArray2[n17];
                    char c4 = '\0';
                    switch (n18 % 5) {
                        case 0: {
                            c4 = '\u0018';
                            break;
                        }
                        case 1: {
                            c4 = '<';
                            break;
                        }
                        case 2: {
                            c4 = ' ';
                            break;
                        }
                        case 3: {
                            c4 = '\t';
                            break;
                        }
                        default: {
                            c4 = '\u0005';
                            break;
                        }
                    }
                    charArray2[length2] = (char)(c3 ^ c4);
                    ++n18;
                } while (n16 == 0);
            }
            if (n16 <= n18) {
                a = TimeZone.getTimeZone(new String(charArray2).intern());
                return;
            }
            continue;
        }
    }
}
